LICENSE
README.rst
setup.py
django_cpserver/__init__.py
django_cpserver/management/__init__.py
django_cpserver/management/commands/__init__.py
django_cpserver/management/commands/runcpserver.py
django_cpserver_op.egg-info/PKG-INFO
django_cpserver_op.egg-info/SOURCES.txt
django_cpserver_op.egg-info/dependency_links.txt
django_cpserver_op.egg-info/requires.txt
django_cpserver_op.egg-info/top_level.txt