Metadata-Version: 1.0
Name: django-cpserver-op
Version: 1.2.1
Summary: Management commands for serving Django via CherryPy's built-in WSGI server modified for OpenProximity
Home-page: https://github.com/OpenProximity/django-cpserver
Author: Peter Baumgartner
Author-email: pete@lincolnloop.com
License: BSD
Platform: UNKNOWN
Classifier: Development Status :: 5 - Production/Stable
Classifier: Framework :: CherryPy
Classifier: Framework :: Django
Classifier: Intended Audience :: Developers
Classifier: License :: OSI Approved :: BSD License
Classifier: Programming Language :: Python
